dlprime/__init__.py
dlprime/activation.py
dlprime/data.py
dlprime/dl.py
dlprime/ml.py
dlprime/testing.py
dlprime-0.1.0.dist-info/METADATA
dlprime-0.1.0.dist-info/WHEEL
dlprime-0.1.0.dist-info/top_level.txt
dlprime-0.1.0.dist-info/RECORD
